company_name_matching2/__init__.py
company_name_matching2/abbreviations.json
company_name_matching2/elf_company.csv
company_name_matching2/matching_function.py
company_name_matching2/data/abbreviations.json
company_name_matching2/data/elf_company.csv
company_name_matching2-0.0.6.dist-info/LICENSE
company_name_matching2-0.0.6.dist-info/METADATA
company_name_matching2-0.0.6.dist-info/WHEEL
company_name_matching2-0.0.6.dist-info/top_level.txt
company_name_matching2-0.0.6.dist-info/RECORD
