Metadata-Version: 2.1
Name: company-name-matching2
Version: 0.0.6
Summary: Returns a score of 2 companies to be the same
Home-page: UNKNOWN
Author: camillebrl (Camille Barboule)
Author-email: camille.barboule@gmail.com
License: UNKNOWN
Keywords: python,companies,matching,duplicates,names,cleaning
Platform: UNKNOWN
Classifier: Development Status :: 1 - Planning
Classifier: Intended Audience :: Developers
Classifier: Programming Language :: Python :: 3
Classifier: Operating System :: Unix
Classifier: Operating System :: MacOS :: MacOS X
Classifier: Operating System :: Microsoft :: Windows
License-File: LICENSE
Requires-Dist: fuzzywuzzy
